package_histmatch/__init__.py
package_histmatch/hist_match.py
package_histmatch/test.py
package_histmatch-0.0.1.dist-info/licenses/LICENCE
package_histmatch-0.0.1.dist-info/METADATA
package_histmatch-0.0.1.dist-info/WHEEL
package_histmatch-0.0.1.dist-info/top_level.txt
package_histmatch-0.0.1.dist-info/RECORD
