Metadata-Version: 2.4
Name: package_histmatch
Version: 0.0.1
Summary: My short description
Home-page: https://github.com/Nayarah/simple-package-template.git
Author: Nayara
Author-email: nayara_franco_almeida@hotmail.com
Requires-Python: >=3.8
License-File: LICENCE
Requires-Dist: scikit-image
Requires-Dist: matplotlib
Dynamic: author
Dynamic: author-email
Dynamic: description
Dynamic: description-content-type
Dynamic: home-page
Dynamic: license-file
Dynamic: requires-dist
Dynamic: requires-python
Dynamic: summary
